simple_memory_cache.py
simple_memory_cache-1.0.0.dist-info/LICENSE
simple_memory_cache-1.0.0.dist-info/METADATA
simple_memory_cache-1.0.0.dist-info/WHEEL
simple_memory_cache-1.0.0.dist-info/top_level.txt
simple_memory_cache-1.0.0.dist-info/RECORD
