Metadata-Version: 2.1
Name: simple-memory-cache
Version: 1.0.0
Summary: Dead Simple Memory Cache
Home-page: https://gitlab.com/tackv/simple-memory-cache
Author: William Laroche
Author-email: william.laroche@tackv.ca
Maintainer: William Laroche
Maintainer-email: william.laroche@tackv.ca
License: UNKNOWN
Platform: UNKNOWN
